droughtmonitor/__about__.py
droughtmonitor/__init__.py
droughtmonitor/test_usdm.py
droughtmonitor/usdm.py
droughtmonitor/data/fips_codes.csv
droughtmonitor/data/update_fips_codes.R
droughtmonitor-0.1.5.dist-info/METADATA
droughtmonitor-0.1.5.dist-info/WHEEL
droughtmonitor-0.1.5.dist-info/licenses/LICENSE.txt
droughtmonitor-0.1.5.dist-info/RECORD
