Metadata-Version: 2.4
Name: droughtmonitor
Version: 0.1.5
Summary: A python-based API wrapper for U.S. Drought Monitor
Project-URL: Documentation, https://github.com/dylan-turner25/droughtmonitor#readme
Project-URL: Issues, https://github.com/dylan-turner25/droughtmonitor/issues
Project-URL: Source, https://github.com/dylan-turner25/droughtmonitor
Author-email: Dylan Turner <dylan.turner3@outlook.com>
License-Expression: MIT
License-File: LICENSE.txt
Keywords: drought,drought monitor
Classifier: Development Status :: 4 - Beta
Classifier: Programming Language :: Python
Classifier: Programming Language :: Python :: 3
Classifier: Programming Language :: Python :: 3.9
Classifier: Programming Language :: Python :: 3.10
Classifier: Programming Language :: Python :: 3.11
Classifier: Programming Language :: Python :: 3.12
Classifier: Programming Language :: Python :: 3.13
Requires-Python: >=3.9
Requires-Dist: geopandas>=1.0.1
Requires-Dist: pandas>=2.2.3
Requires-Dist: requests>=2.32.3
Requires-Dist: tqdm>=4.67.1
Provides-Extra: development
Requires-Dist: pytest-mock>=3.0.0; extra == 'development'
Requires-Dist: pytest>=8.3.4; extra == 'development'
